humdroid/__init__.py
humdroid/IPC/CVRequester.py
humdroid/IPC/CVServer.py
humdroid/IPC/IPCSocket.py
humdroid/IPC/__init__.py
humdroid/wrappers/ScrcpyWrapper.py
humdroid/wrappers/__init__.py
humdroid-0.2.1.dist-info/LICENSE
humdroid-0.2.1.dist-info/METADATA
humdroid-0.2.1.dist-info/WHEEL
humdroid-0.2.1.dist-info/top_level.txt
humdroid-0.2.1.dist-info/RECORD
