Metadata-Version: 2.1
Name: humdroid
Version: 0.2.1
Summary: Programmatically control Android like a Human
Author-email: Diego Contreras <smarttdiego@gmail.com>
License: Apache License
Project-URL: Homepage, https://github.com/Desperationis/humdroid
Project-URL: Bug Tracker, https://github.com/Desperationis/humdroid/issues
Classifier: Programming Language :: Python :: 3
Classifier: License :: OSI Approved :: Apache Software License
Classifier: Operating System :: POSIX :: Linux
Requires-Python: >=3.7
License-File: LICENSE
Requires-Dist: pillow
Requires-Dist: adbutils
Requires-Dist: scrcpy-client
